matita/office/__init__.py
matita/office/access.py
matita/office/excel.py
matita/office/office.py
matita/office/outlook.py
matita/office/powerpoint.py
matita/office/word.py
matita/reference/__init__.py
matita/reference/markdown.py
matita/reference/models.py
matita-1.0.3.dist-info/METADATA
matita-1.0.3.dist-info/WHEEL
matita-1.0.3.dist-info/licenses/LICENSE.md
matita-1.0.3.dist-info/RECORD
