Metadata-Version: 2.4
Name: matita
Version: 1.0.3
Summary: Python wrapper for the VBA Object library
Project-URL: Homepage, https://matita.readthedocs.io
Project-URL: Documentation, https://matita.readthedocs.io/en/latest/documentation
Project-URL: GitHub, https://github.com/lucafrance/matita
Author-email: Luca Franceschini <lucaf@lucaf.eu>
License-Expression: GPL-3.0-only
License-File: LICENSE.md
Classifier: Operating System :: Microsoft :: Windows
Classifier: Programming Language :: Python :: 3
Classifier: Topic :: Office/Business :: Office Suites
Requires-Python: >=3.13
Requires-Dist: pywin32
